elyx/__init__.py
elyx/cryptor.py
elyx/main.py
elyx/ui.py
elyx/utils.py
elyx-0.1.0.dist-info/licenses/LICENSE
tests/__init__.py
tests/test_cryptor.py
elyx-0.1.0.dist-info/METADATA
elyx-0.1.0.dist-info/WHEEL
elyx-0.1.0.dist-info/entry_points.txt
elyx-0.1.0.dist-info/top_level.txt
elyx-0.1.0.dist-info/RECORD
