Metadata-Version: 2.4
Name: elyx
Version: 0.1.0
Summary: A secure terminal-based encryption/decryption tool
Home-page: https://github.com/yourusername/elyx
Author: princecodes
Author-email: princecodes@duck.com
Project-URL: Bug Reports, https://github.com/yourusername/elyx/issues
Project-URL: Source, https://github.com/yourusername/elyx
Keywords: encryption decryption security cryptography terminal cli
Classifier: Development Status :: 4 - Beta
Classifier: Intended Audience :: End Users/Desktop
Classifier: Topic :: Security :: Cryptography
Classifier: License :: OSI Approved :: MIT License
Classifier: Programming Language :: Python :: 3
Classifier: Programming Language :: Python :: 3.8
Classifier: Programming Language :: Python :: 3.9
Classifier: Programming Language :: Python :: 3.10
Classifier: Programming Language :: Python :: 3.11
Classifier: Programming Language :: Python :: 3.12
Classifier: Operating System :: OS Independent
Classifier: Environment :: Console
Requires-Python: >=3.8
License-File: LICENSE
Requires-Dist: cryptography>=41.0.0
Requires-Dist: rich>=13.7.0
Requires-Dist: click>=8.1.0
Requires-Dist: pyperclip>=1.8.2
Dynamic: author
Dynamic: author-email
Dynamic: classifier
Dynamic: description
Dynamic: description-content-type
Dynamic: home-page
Dynamic: keywords
Dynamic: license-file
Dynamic: project-url
Dynamic: requires-dist
Dynamic: requires-python
Dynamic: summary
